mps_flash_attn/_C.cpython-314-darwin.so
mps_flash_attn/__init__.py
mps_flash_attn/benchmark.py
mps_flash_attn/csrc/mps_flash_attn.mm
mps_flash_attn/kernels/06c421e7a01418cf64aafa07f6b1df0558148583959c596d9a7ce260987f89f0.metallib
mps_flash_attn/kernels/09b9615289be632fdf05444004a0b3b67fb1b70b05a7e0fce8e0ba3a95e3921c.metallib
mps_flash_attn/kernels/0c36461301fb52cbad786d0642b020ad2bfc7229b487ccb5dff44d198423b347.metallib
mps_flash_attn/kernels/2ca9312d1151f792e1a95617db9186928300e3d0ffbe016f0ad53b62ab840bac.metallib
mps_flash_attn/kernels/73254c55475c6b7f7b009f095398994b1f9ae8215beafcf810f100357ccc99b2.metallib
mps_flash_attn/kernels/73254c55475c6b7f7b009f095398994b1f9ae8215beafcf810f100357ccc99b2_1024_1024.bin
mps_flash_attn/kernels/73254c55475c6b7f7b009f095398994b1f9ae8215beafcf810f100357ccc99b2_2048_2048.bin
mps_flash_attn/kernels/73254c55475c6b7f7b009f095398994b1f9ae8215beafcf810f100357ccc99b2_4096_4096.bin
mps_flash_attn/kernels/73254c55475c6b7f7b009f095398994b1f9ae8215beafcf810f100357ccc99b2_512_512.bin
mps_flash_attn/kernels/73254c55475c6b7f7b009f095398994b1f9ae8215beafcf810f100357ccc99b2_8192_8192.bin
mps_flash_attn/kernels/771935bf47d248650e287da82bc82e04bff7c4c52964823e7a12462ccd23408e.metallib
mps_flash_attn/kernels/975aece2b4d3d78035be08a0735a7deacf2e544adee5af81c9c0a3a42a926129.metallib
mps_flash_attn/kernels/a5e2c5c401e3872af0899c1fb3e30b5f52a6070fc49c9dac02982cc1c2f25849.metallib
mps_flash_attn/kernels/ac4573fb201e92310867c59bd569a8ae68f859d60a9352d9d4d5d41c1547c83c.metallib
mps_flash_attn/kernels/adc0f77ff05156bbda8fe78afd9ba8a8d3c890ba8fea0902ae79a6ae8c4f04c3.metallib
mps_flash_attn/kernels/eab4f40de4b0ebd2765b41c25dba7ccab5db4abf6a6eb87d76fff7b5e0829b2f.metallib
mps_flash_attn/kernels/eab4f40de4b0ebd2765b41c25dba7ccab5db4abf6a6eb87d76fff7b5e0829b2f_1024_1024.bin
mps_flash_attn/kernels/eab4f40de4b0ebd2765b41c25dba7ccab5db4abf6a6eb87d76fff7b5e0829b2f_2048_2048.bin
mps_flash_attn-0.2.3.dist-info/licenses/LICENSE
mps_flash_attn-0.2.3.dist-info/METADATA
mps_flash_attn-0.2.3.dist-info/WHEEL
mps_flash_attn-0.2.3.dist-info/top_level.txt
mps_flash_attn-0.2.3.dist-info/RECORD
