Metadata-Version: 2.4
Name: mps-flash-attn
Version: 0.2.3
Summary: Flash Attention for PyTorch on Apple Silicon (M1/M2/M3/M4)
Author: imperatormk
License-Expression: MIT
Project-URL: Homepage, https://github.com/mpsops/mps-flash-attention
Project-URL: Repository, https://github.com/mpsops/mps-flash-attention
Project-URL: Issues, https://github.com/mpsops/mps-flash-attention/issues
Keywords: flash-attention,apple-silicon,pytorch,mps,metal,transformer,attention
Classifier: Development Status :: 4 - Beta
Classifier: Intended Audience :: Developers
Classifier: Intended Audience :: Science/Research
Classifier: Operating System :: MacOS :: MacOS X
Classifier: Programming Language :: Python :: 3
Classifier: Programming Language :: Python :: 3.10
Classifier: Programming Language :: Python :: 3.11
Classifier: Programming Language :: Python :: 3.12
Classifier: Topic :: Scientific/Engineering :: Artificial Intelligence
Requires-Python: >=3.10
License-File: LICENSE
Requires-Dist: torch>=2.0.0
Dynamic: license-file
